qbwc/__init__.py
qbwc/app_settings.py
qbwc/asgi.py
qbwc/urls.py
qbwc/utils.py
qbwc/views.py
qbwc/wsgi.py
qbwc/templates/qbwc/support.html
qbwc-0.1.dist-info/LICENSE.md
qbwc-0.1.dist-info/METADATA
qbwc-0.1.dist-info/WHEEL
qbwc-0.1.dist-info/top_level.txt
qbwc-0.1.dist-info/RECORD
