Metadata-Version: 2.1
Name: qbwc
Version: 0.1
Summary: QuickBooks Desktop Webconnector Implementation
Home-page: https://www.github.com/bill-ash/qbwc
Author: Bill Ash
Author-email: bill@overco.net
License: MIT
Classifier: Environment :: Web Environment
Classifier: Framework :: Django
Classifier: Framework :: Django :: 4.2
Classifier: Intended Audience :: Developers
Classifier: License :: OSI Approved :: BSD License
Classifier: Operating System :: OS Independent
Classifier: Programming Language :: Python
Classifier: Programming Language :: Python :: 3
Classifier: Programming Language :: Python :: 3 :: Only
Classifier: Programming Language :: Python :: 3.9
Classifier: Topic :: Internet :: WWW/HTTP
Classifier: Topic :: Internet :: WWW/HTTP :: Dynamic Content
Requires-Python: >=3.9
License-File: LICENSE.md
Requires-Dist: Django (>=4.2)
Requires-Dist: lxml (>=4.9.2)
Requires-Dist: spyne (>=2.14.0)
